{
  "id": "about-system/requirements",
  "title": "Requirements",
  "description": "Work in progress...",
  "source": "@site/docs/about-system/requirements.md",
  "sourceDirName": "about-system",
  "slug": "/about-system/requirements",
  "permalink": "/comunication_website/docs/about-system/requirements",
  "draft": false,
  "unlisted": false,
  "tags": [],
  "version": "current",
  "sidebarPosition": 2,
  "frontMatter": {
    "sidebar_position": 2
  },
  "sidebar": "tutorialSidebar",
  "previous": {
    "title": "Database",
    "permalink": "/comunication_website/docs/about-system/database"
  },
  "next": {
    "title": "Architecture",
    "permalink": "/comunication_website/docs/about-system/architecture"
  }
}